KdnEngine/__init__.py
KdnEngine/run_engine.py
KdnEngine/engine/__init__.py
KdnEngine/engine/animation.py
KdnEngine/engine/audio.py
KdnEngine/engine/input.py
KdnEngine/engine/main.py
KdnEngine/engine/physics.py
KdnEngine/engine/rendering.py
KdnEngine/engine/scene.py
KdnEngine/engine/scripting.py
KdnEngine/engine/ui.py
KdnEngine/game_ui/asset_importer_ui.py
KdnEngine/game_ui/level_editor_ui.py
KdnEngine/game_ui/scene_manager_ui.py
KdnEngine/tests/__init__.py
KdnEngine/tests/test_animation.py
KdnEngine/tests/test_audio.py
KdnEngine/tests/test_input.py
KdnEngine/tests/test_physics.py
KdnEngine/tests/test_rendering.py
KdnEngine/tests/test_scene.py
KdnEngine/tests/test_scripting.py
KdnEngine/tests/test_ui.py
KdnEngine/tools/__init__.py
KdnEngine/tools/asset_importer.py
KdnEngine/tools/level_editor.py
KdnEngine/ui/ui_elements.py
KdnEngine/ui/ui_manager.py
KdnEngine-0.7.dist-info/LICENSE
KdnEngine-0.7.dist-info/METADATA
KdnEngine-0.7.dist-info/WHEEL
KdnEngine-0.7.dist-info/top_level.txt
KdnEngine-0.7.dist-info/RECORD
